{
  "$schema": "https://ui.shadcn.com/schema/registry-item.json",
  "name": "ai-chat-interface",
  "type": "registry:component",
  "title": "AI Chat Interface",
  "description": "Chat input with attachments, model selector, and accessible controls",
  "registryDependencies": [
    "button",
    "textarea"
  ],
  "dependencies": [
    "framer-motion",
    "lucide-react",
    "react"
  ],
  "files": [
    {
      "path": "components/ai-chat-interface.tsx",
      "content": "// Error: Could not read file components/ai-chat-interface.tsx\n// File not found: components/ai-chat-interface.tsx",
      "type": "registry:component",
      "target": "ai-chat-interface.tsx"
    }
  ]
}